{
  "$schema": "https://raw.githubusercontent.com/devcontainers/spec/main/schemas/devContainer.schema.json",
  "name": "ClusterTool Cluster",
  "image": "ghcr.io/trueforge-org/devcontainer:3.0.2@sha256:3ae2c17d5ae37b5d045902b0819809d290547557f89339e3d672ee2c07c062a2",
  "postCreateCommand": {
    "setup": "bash ${containerWorkspaceFolder}/.devcontainer/postCreateCommand.sh"
  },
  "postStartCommand": {
    "git": "git config --global --add safe.directory ${containerWorkspaceFolder}"
  },
  "postAttachCommand": "fish",
  "updateRemoteUserUID": false,
  "runArgs": [
    "--privileged"
  ]
}